{"history":{"2024-03-04":{"words":185,"characters":1239,"sentences":21,"pages":0.6000000000000001,"files":4,"footnotes":0,"citations":0,"totalWords":983,"totalCharacters":6415,"totalSentences":50,"totalFootnotes":19633,"totalCitations":19633,"totalPages":3.2}},"modifiedFiles":{"OpenCorporation.md":{"words":{"initial":578,"current":611},"characters":{"initial":3450,"current":3651},"sentences":{"initial":26,"current":30},"footnotes":{"initial":0,"current":0},"citations":{"initial":0,"current":0},"pages":{"initial":1.9,"current":2}},"Challenges.md":{"words":{"initial":0,"current":0},"characters":{"initial":1,"current":3},"sentences":{"initial":0,"current":0},"footnotes":{"initial":0,"current":0},"citations":{"initial":0,"current":0},"pages":{"initial":0,"current":0}},"ScratchPad.md":{"words":{"initial":0,"current":152},"characters":{"initial":1,"current":1037},"sentences":{"initial":0,"current":17},"footnotes":{"initial":0,"current":0},"citations":{"initial":0,"current":0},"pages":{"initial":0,"current":0.5}}}}